custom_alu/rtl/custom_alu.sv
// =============================================================================
// Custom ALU Design for CROC Platform
// File: custom_alu.sv
// Description: 32-bit ALU supporting ADD, SUB, AND, OR, XOR, SHL, SHR ops
//              Designed to integrate with CROC SoC via simple register interface
// =============================================================================

`timescale 1ns/1ps

module custom_alu #(
    parameter DATA_WIDTH = 32
) (
    input  logic                   clk_i,
    input  logic                   rst_ni,      // Active-low reset

    // Register interface (memory-mapped via CROC APB)
    input  logic [DATA_WIDTH-1:0]  operand_a_i, // Operand A
    input  logic [DATA_WIDTH-1:0]  operand_b_i, // Operand B
    input  logic [3:0]             op_sel_i,    // Operation select
    input  logic                   valid_i,     // Input valid strobe

    // Outputs
    output logic [DATA_WIDTH-1:0]  result_o,    // ALU result
    output logic                   zero_o,      // Zero flag
    output logic                   carry_o,     // Carry/overflow flag
    output logic                   ready_o      // Result ready
);

    // Operation encoding
   // typedef enum logic [3:0] {
   //     ALU_ADD = 4'h0,
   //     ALU_SUB = 4'h1,
   //     ALU_AND = 4'h2,
   //     ALU_OR  = 4'h3,
   //     ALU_XOR = 4'h4,
   //     ALU_SHL = 4'h5,
   //     ALU_SHR = 4'h6,
   //     ALU_SRA = 4'h7,  // Arithmetic right shift
   //     ALU_NOR = 4'h8,
   //     ALU_XNOR= 4'h9
   // } alu_op_e;

    // Internal signals
    logic [DATA_WIDTH:0]   result_extended;  // Extra bit for carry
    logic [DATA_WIDTH-1:0] result_q;
    logic                  carry_q, zero_q, ready_q;

    // Combinational ALU logic
    always_comb begin : alu_operation
        result_extended = '0;
        case (op_sel_i)
            4'h0: result_extended = {1'b0, operand_a_i} + {1'b0, operand_b_i};  // ADD
            4'h1: result_extended = {1'b0, operand_a_i} - {1'b0, operand_b_i};  // SUB
            4'h2: result_extended = {1'b0, operand_a_i  & operand_b_i};          // AND
            4'h3: result_extended = {1'b0, operand_a_i  | operand_b_i};          // OR
            4'h4: result_extended = {1'b0, operand_a_i  ^ operand_b_i};          // XOR
            4'h5: result_extended = {1'b0, operand_a_i << operand_b_i[4:0]};     // SHL
            4'h6: result_extended = {1'b0, operand_a_i >> operand_b_i[4:0]};     // SHR
            4'h7: result_extended = {1'b0, $signed(operand_a_i) >>> operand_b_i[4:0]}; // SRA
            4'h8: result_extended = {1'b0, ~(operand_a_i | operand_b_i)};        // NOR
            4'h9: result_extended = {1'b0, ~(operand_a_i ^ operand_b_i)};        // XNOR
            default: result_extended = '0;
        endcase
    end

    // Registered output stage
    always_ff @(posedge clk_i or negedge rst_ni) begin : output_reg
        if (!rst_ni) begin
            result_q <= '0;
            carry_q  <= 1'b0;
            zero_q   <= 1'b0;
            ready_q  <= 1'b0;
        end else begin
            ready_q  <= valid_i;
            if (valid_i) begin
                result_q <= result_extended[DATA_WIDTH-1:0];
                carry_q  <= result_extended[DATA_WIDTH];
                zero_q   <= (result_extended[DATA_WIDTH-1:0] == '0);
            end
        end
    end

    assign result_o = result_q;
    assign carry_o  = carry_q;
    assign zero_o   = zero_q;
    assign ready_o  = ready_q;

endmodule : custom_alu

custom_alu/rtl/custom_alu_apb_wrapper.sv
// =============================================================================
// APB Wrapper for Custom ALU - CROC Platform Integration
// File: custom_alu_apb_wrapper.sv
// Description: Wraps the custom ALU with an APB3 slave interface so it can be
//              memory-mapped into CROC's peripheral address space.
//
// Register Map (base + offset):
//   0x00 - OPERAND_A   (R/W) - 32-bit operand A
//   0x04 - OPERAND_B   (R/W) - 32-bit operand B
//   0x08 - OP_CTRL     (R/W) - [3:0] op_sel, [4] valid trigger
//   0x0C - RESULT      (RO)  - 32-bit result
//   0x10 - STATUS      (RO)  - [0] ready, [1] zero, [2] carry
// =============================================================================

`timescale 1ns/1ps

module custom_alu_apb_wrapper #(
    parameter APB_ADDR_WIDTH = 32,
    parameter APB_DATA_WIDTH = 32
) (
    input  logic                      clk_i,
    input  logic                      rst_ni,

    // APB Slave Interface
    input  logic [APB_ADDR_WIDTH-1:0] apb_paddr_i,
    input  logic                      apb_psel_i,
    input  logic                      apb_penable_i,
    input  logic                      apb_pwrite_i,
    input  logic [APB_DATA_WIDTH-1:0] apb_pwdata_i,
    output logic [APB_DATA_WIDTH-1:0] apb_prdata_o,
    output logic                      apb_pready_o,
    output logic                      apb_pslverr_o
);

    // Register addresses (word-addressed offsets)
    localparam ADDR_OPERAND_A = 3'h0;
    localparam ADDR_OPERAND_B = 3'h1;
    localparam ADDR_OP_CTRL   = 3'h2;
    localparam ADDR_RESULT    = 3'h3;
    localparam ADDR_STATUS    = 3'h4;

    // Internal registers
    logic [31:0] reg_operand_a, reg_operand_b;
    logic [4:0]  reg_op_ctrl;
    logic [31:0] alu_result;
    logic        alu_zero, alu_carry, alu_ready;
    logic        alu_valid_pulse;

    // Address decode (word-aligned: bits [4:2])
    logic [2:0] word_addr;
    assign word_addr = apb_paddr_i[4:2];

    // APB write logic
    always_ff @(posedge clk_i or negedge rst_ni) begin
        if (!rst_ni) begin
            reg_operand_a  <= '0;
            reg_operand_b  <= '0;
            reg_op_ctrl    <= '0;
            alu_valid_pulse <= 1'b0;
        end else begin
            alu_valid_pulse <= 1'b0;  // Single-cycle pulse

            if (apb_psel_i && apb_penable_i && apb_pwrite_i) begin
                case (word_addr)
                    ADDR_OPERAND_A: reg_operand_a <= apb_pwdata_i;
                    ADDR_OPERAND_B: reg_operand_b <= apb_pwdata_i;
                    ADDR_OP_CTRL: begin
                        reg_op_ctrl     <= apb_pwdata_i[4:0];
                        alu_valid_pulse <= apb_pwdata_i[4];  // bit4 triggers compute
                    end
                    default: ; // Ignore writes to RO registers
                endcase
            end
        end
    end

    // APB read logic
    always_comb begin
        apb_prdata_o = '0;
        if (apb_psel_i && !apb_pwrite_i) begin
            case (word_addr)
                ADDR_OPERAND_A: apb_prdata_o = reg_operand_a;
                ADDR_OPERAND_B: apb_prdata_o = reg_operand_b;
                ADDR_OP_CTRL:   apb_prdata_o = {27'b0, reg_op_ctrl};
                ADDR_RESULT:    apb_prdata_o = alu_result;
                ADDR_STATUS:    apb_prdata_o = {29'b0, alu_carry, alu_zero, alu_ready};
                default:        apb_prdata_o = 32'hDEAD_BEEF;
            endcase
        end
    end

    assign apb_pready_o  = 1'b1;   // Zero wait states
    assign apb_pslverr_o = 1'b0;   // No error

    // Instantiate ALU core
    custom_alu #(
        .DATA_WIDTH(32)
    ) u_alu (
        .clk_i       (clk_i),
        .rst_ni      (rst_ni),
        .operand_a_i (reg_operand_a),
        .operand_b_i (reg_operand_b),
        .op_sel_i    (reg_op_ctrl[3:0]),
        .valid_i     (alu_valid_pulse),
        .result_o    (alu_result),
        .zero_o      (alu_zero),
        .carry_o     (alu_carry),
        .ready_o     (alu_ready)
    );

endmodule : custom_alu_apb_wrapper

custom_alu/rtl/tb/tb_custom_alu_apb.sv
// =============================================================================
// Testbench for custom_alu_apb_wrapper
// File: tb_custom_alu_apb.sv
// Tests: APB write/read register access, ALU operations via APB interface
// Compatible with: Verilator, ModelSim, Xcelium, VCS
// =============================================================================

`timescale 1ns/1ps

module tb_custom_alu_apb;

    // -------------------------------------------------------------------------
    // DUT signals
    // -------------------------------------------------------------------------
    logic        clk, rst_n;
    logic [31:0] apb_paddr;
    logic        apb_psel, apb_penable, apb_pwrite;
    logic [31:0] apb_pwdata;
    logic [31:0] apb_prdata;
    logic        apb_pready, apb_pslverr;

    // -------------------------------------------------------------------------
    // DUT instantiation
    // -------------------------------------------------------------------------
    custom_alu_apb_wrapper u_dut (
        .clk_i          (clk),
        .rst_ni         (rst_n),
        .apb_paddr_i    (apb_paddr),
        .apb_psel_i     (apb_psel),
        .apb_penable_i  (apb_penable),
        .apb_pwrite_i   (apb_pwrite),
        .apb_pwdata_i   (apb_pwdata),
        .apb_prdata_o   (apb_prdata),
        .apb_pready_o   (apb_pready),
        .apb_pslverr_o  (apb_pslverr)
    );

    // -------------------------------------------------------------------------
    // Clock generation: 100 MHz
    // -------------------------------------------------------------------------
    initial clk = 0;
    always #5 clk = ~clk;

    // -------------------------------------------------------------------------
    // Test result tracking
    // -------------------------------------------------------------------------
    int pass_count = 0;
    int fail_count = 0;

    // -------------------------------------------------------------------------
    // APB Tasks
    // -------------------------------------------------------------------------

    // APB Write task
    task automatic apb_write(input logic [31:0] addr, input logic [31:0] data);
        @(posedge clk);
        apb_paddr   = addr;
        apb_pwdata  = data;
        apb_pwrite  = 1'b1;
        apb_psel    = 1'b1;
        apb_penable = 1'b0;
        @(posedge clk);
        apb_penable = 1'b1;
        @(posedge clk);
        while (!apb_pready) @(posedge clk);
        apb_psel    = 1'b0;
        apb_penable = 1'b0;
        apb_pwrite  = 1'b0;
    endtask

    // APB Read task
    task automatic apb_read(input logic [31:0] addr, output logic [31:0] data);
        @(posedge clk);
        apb_paddr   = addr;
        apb_pwrite  = 1'b0;
        apb_psel    = 1'b1;
        apb_penable = 1'b0;
        @(posedge clk);
        apb_penable = 1'b1;
        @(posedge clk);
        while (!apb_pready) @(posedge clk);
        data        = apb_prdata;
        apb_psel    = 1'b0;
        apb_penable = 1'b0;
    endtask

    // Check task
    task automatic check(
        input string  test_name,
        input logic [31:0] got,
        input logic [31:0] expected
    );
        if (got === expected) begin
            $display("[PASS] %s | got=0x%08h expected=0x%08h", test_name, got, expected);
            pass_count++;
        end else begin
            $display("[FAIL] %s | got=0x%08h expected=0x%08h", test_name, got, expected);
            fail_count++;
        end
    endtask

    // Run ALU operation via APB and return result
    task automatic run_alu(
        input  logic [31:0] op_a,
        input  logic [31:0] op_b,
        input  logic [3:0]  op,
        output logic [31:0] result,
        output logic [31:0] status
    );
        apb_write(32'h00, op_a);          // Write operand A
        apb_write(32'h04, op_b);          // Write operand B
        apb_write(32'h08, {27'b0, 1'b1, op}); // op_sel + trigger bit
        repeat(3) @(posedge clk);         // Wait for pipeline
        apb_read(32'h0C, result);         // Read result
        apb_read(32'h10, status);         // Read status flags
    endtask

    // -------------------------------------------------------------------------
    // Test sequence
    // -------------------------------------------------------------------------
    initial begin
        // Dump waveforms
        $dumpfile("tb_custom_alu_apb.vcd");
        $dumpvars(0, tb_custom_alu_apb);

        // Initialize APB bus
        apb_paddr   = '0;
        apb_psel    = '0;
        apb_penable = '0;
        apb_pwrite  = '0;
        apb_pwdata  = '0;

        // Reset
        rst_n = 0;
        repeat(5) @(posedge clk);
        rst_n = 1;
        repeat(2) @(posedge clk);

        $display("\n========================================");
        $display("  CROC Custom ALU APB Testbench");
        $display("========================================\n");

        // ---------------------------------------------------------------
        // TEST GROUP 1: Register Read/Write
        // ---------------------------------------------------------------
        $display("--- TEST GROUP 1: Register R/W ---");

        // Write and read back operand A
        apb_write(32'h00, 32'hABCD_1234);
        begin
            logic [31:0] rd;
            apb_read(32'h00, rd);
            check("REG_WRITE_OPERAND_A", rd, 32'hABCD_1234);
        end

        // Write and read back operand B
        apb_write(32'h04, 32'h5678_EFFF);
        begin
            logic [31:0] rd;
            apb_read(32'h04, rd);
            check("REG_WRITE_OPERAND_B", rd, 32'h5678_EFFF);
        end

        // Write op control (op only, no trigger)
        apb_write(32'h08, 32'h0000_0003); // OR operation
        begin
            logic [31:0] rd;
            apb_read(32'h08, rd);
            check("REG_WRITE_OP_CTRL", rd, 32'h0000_0003);
        end

        // ---------------------------------------------------------------
        // TEST GROUP 2: ALU Operations
        // ---------------------------------------------------------------
        $display("\n--- TEST GROUP 2: ALU Operations ---");

        begin
            logic [31:0] res, status;

            // ADD: 100 + 200 = 300
            run_alu(32'd100, 32'd200, 4'h0, res, status);
            check("ALU_ADD_100+200", res, 32'd300);

            // ADD with carry: 0xFFFFFFFF + 1 => 0, carry=1
            run_alu(32'hFFFF_FFFF, 32'h1, 4'h0, res, status);
            check("ALU_ADD_OVERFLOW_RESULT", res, 32'h0000_0000);
            check("ALU_ADD_OVERFLOW_CARRY",  status[2], 1'b1);
            check("ALU_ADD_OVERFLOW_ZERO",   status[1], 1'b1);

            // SUB: 500 - 200 = 300
            run_alu(32'd500, 32'd200, 4'h1, res, status);
            check("ALU_SUB_500-200", res, 32'd300);

            // SUB to zero: same operands
            run_alu(32'hDEAD_BEEF, 32'hDEAD_BEEF, 4'h1, res, status);
            check("ALU_SUB_ZERO_RESULT", res, 32'h0);
            check("ALU_SUB_ZERO_FLAG",   status[1], 1'b1);

            // AND
            run_alu(32'hFF00_FF00, 32'h0FF0_0FF0, 4'h2, res, status);
            check("ALU_AND", res, 32'h0F00_0F00);

            // OR
            run_alu(32'hA0A0_A0A0, 32'h0B0B_0B0B, 4'h3, res, status);
            check("ALU_OR", res, 32'hABAB_ABAB);

            // XOR: same values = 0
            run_alu(32'h1234_5678, 32'h1234_5678, 4'h4, res, status);
            check("ALU_XOR_SAME_ZERO", res, 32'h0);
            check("ALU_XOR_ZERO_FLAG", status[1], 1'b1);

            // SHL: 1 << 8 = 0x100
            run_alu(32'h0000_0001, 32'd8, 4'h5, res, status);
            check("ALU_SHL_1<<8", res, 32'h0000_0100);

            // SHR: 0x100 >> 4 = 0x10
            run_alu(32'h0000_0100, 32'd4, 4'h6, res, status);
            check("ALU_SHR_0x100>>4", res, 32'h0000_0010);

            // SRA: preserve sign on negative number
            run_alu(32'h8000_0000, 32'd1, 4'h7, res, status);
            check("ALU_SRA_NEG", res, 32'hC000_0000); // Arithmetic: MSB preserved
        end

        // ---------------------------------------------------------------
        // TEST GROUP 3: Status flags edge cases
        // ---------------------------------------------------------------
        $display("\n--- TEST GROUP 3: Status Flags ---");
        begin
            logic [31:0] res, status;

            // Check ready flag
            run_alu(32'd1, 32'd1, 4'h0, res, status);
            check("STATUS_READY_FLAG", status[0], 1'b1);

            // NOR: ~(A | B)
            run_alu(32'h0000_0000, 32'h0000_0000, 4'h8, res, status);
            check("ALU_NOR_ZERO_INPUTS", res, 32'hFFFF_FFFF);
        end

        // ---------------------------------------------------------------
        // Results summary
        // ---------------------------------------------------------------
        $display("\n========================================");
        $display("  RESULTS: %0d PASS | %0d FAIL", pass_count, fail_count);
        $display("========================================\n");

        if (fail_count == 0)
            $display("ALL TESTS PASSED!\n");
        else
            $display("SOME TESTS FAILED - check above.\n");

        $finish;
    end

    // Timeout watchdog
    initial begin
        #500000;
        $display("[ERROR] Simulation timeout!");
        $finish;
    end

endmodule : tb_custom_alu_apb

custom_alu/tb_custom_alu_apb.vcd
$version Generated by VerilatedVcd $end
$timescale 1ps $end
 $scope module TOP $end
  $scope module tb_custom_alu_apb $end
   $var wire 1 > clk $end
   $var wire 1 # rst_n $end
   $var wire 32 $ apb_paddr [31:0] $end
   $var wire 1 % apb_psel $end
   $var wire 1 & apb_penable $end
   $var wire 1 ' apb_pwrite $end
   $var wire 32 ( apb_pwdata [31:0] $end
   $var wire 32 ? apb_prdata [31:0] $end
   $var wire 1 @ apb_pready $end
   $var wire 1 A apb_pslverr $end
   $var wire 32 ) pass_count [31:0] $end
   $var wire 32 * fail_count [31:0] $end
   $scope module u_dut $end
    $var wire 32 B APB_ADDR_WIDTH [31:0] $end
    $var wire 32 B APB_DATA_WIDTH [31:0] $end
    $var wire 1 > clk_i $end
    $var wire 1 # rst_ni $end
    $var wire 32 $ apb_paddr_i [31:0] $end
    $var wire 1 % apb_psel_i $end
    $var wire 1 & apb_penable_i $end
    $var wire 1 ' apb_pwrite_i $end
    $var wire 32 ( apb_pwdata_i [31:0] $end
    $var wire 32 ? apb_prdata_o [31:0] $end
    $var wire 1 @ apb_pready_o $end
    $var wire 1 A apb_pslverr_o $end
    $var wire 3 C ADDR_OPERAND_A [2:0] $end
    $var wire 3 D ADDR_OPERAND_B [2:0] $end
    $var wire 3 E ADDR_OP_CTRL [2:0] $end
    $var wire 3 F ADDR_RESULT [2:0] $end
    $var wire 3 G ADDR_STATUS [2:0] $end
    $var wire 32 3 reg_operand_a [31:0] $end
    $var wire 32 4 reg_operand_b [31:0] $end
    $var wire 5 5 reg_op_ctrl [4:0] $end
    $var wire 32 6 alu_result [31:0] $end
    $var wire 1 7 alu_zero $end
    $var wire 1 8 alu_carry $end
    $var wire 1 9 alu_ready $end
    $var wire 1 : alu_valid_pulse $end
    $var wire 3 + word_addr [2:0] $end
    $scope module u_alu $end
     $var wire 32 B DATA_WIDTH [31:0] $end
     $var wire 1 > clk_i $end
     $var wire 1 # rst_ni $end
     $var wire 32 3 operand_a_i [31:0] $end
     $var wire 32 4 operand_b_i [31:0] $end
     $var wire 4 ; op_sel_i [3:0] $end
     $var wire 1 : valid_i $end
     $var wire 32 6 result_o [31:0] $end
     $var wire 1 7 zero_o $end
     $var wire 1 8 carry_o $end
     $var wire 1 9 ready_o $end
     $var wire 33 < result_extended [32:0] $end
     $var wire 32 6 result_q [31:0] $end
     $var wire 1 8 carry_q $end
     $var wire 1 7 zero_q $end
     $var wire 1 9 ready_q $end
    $upscope $end
   $upscope $end
   $scope module unnamedblk1 $end
    $var wire 32 , rd [31:0] $end
   $upscope $end
   $scope module unnamedblk2 $end
    $var wire 32 - rd [31:0] $end
   $upscope $end
   $scope module unnamedblk3 $end
    $var wire 32 . rd [31:0] $end
   $upscope $end
   $scope module unnamedblk4 $end
    $var wire 32 / res [31:0] $end
    $var wire 32 0 status [31:0] $end
   $upscope $end
   $scope module unnamedblk5 $end
    $var wire 32 1 res [31:0] $end
    $var wire 32 2 status [31:0] $end
   $upscope $end
  $upscope $end
 $upscope $end
$enddefinitions $end


#0
0#
b00000000000000000000000000000000 $
0%
0&
0'
b00000000000000000000000000000000 (
b00000000000000000000000000000000 )
b00000000000000000000000000000000 *
b000 +
b00000000000000000000000000000000 ,
b00000000000000000000000000000000 -
b00000000000000000000000000000000 .
b00000000000000000000000000000000 /
b00000000000000000000000000000000 0
b00000000000000000000000000000000 1
b00000000000000000000000000000000 2
b00000000000000000000000000000000 3
b00000000000000000000000000000000 4
b00000 5
b00000000000000000000000000000000 6
07
08
09
0:
b0000 ;
b000000000000000000000000000000000 <
0>
b00000000000000000000000000000000 ?
1@
0A
b00000000000000000000000000100000 B
b000 C
b001 D
b010 E
b011 F
b100 G
#5000
1>
#10000
0>
#15000
1>
#20000
0>
#25000
1>
#30000
0>
#35000
1>
#40000
0>
#45000
1#
1>
#50000
0>
#55000
1>
#60000
0>
#65000
1>
#70000
0>
#75000
1%
1'
b10101011110011010001001000110100 (
1>
#80000
0>
#85000
1&
b10101011110011010001001000110100 3
b010101011110011010001001000110100 <
1>
#90000
0>
#95000
0%
0&
0'
1>
#100000
0>
#105000
1%
1>
b10101011110011010001001000110100 ?
#110000
0>
#115000
1&
1>
#120000
0>
#125000
0%
0&
b00000000000000000000000000000001 )
b10101011110011010001001000110100 ,
1>
b00000000000000000000000000000000 ?
#130000
0>
#135000
b00000000000000000000000000000100 $
1%
1'
b01010110011110001110111111111111 (
b001 +
1>
#140000
0>
#145000
1&
b01010110011110001110111111111111 4
b100000010010001100000001000110011 <
1>
#150000
0>
#155000
0%
0&
0'
1>
#160000
0>
#165000
1%
1>
b01010110011110001110111111111111 ?
#170000
0>
#175000
1&
1>
#180000
0>
#185000
0%
0&
b00000000000000000000000000000010 )
b01010110011110001110111111111111 -
1>
b00000000000000000000000000000000 ?
#190000
0>
#195000
b00000000000000000000000000001000 $
1%
1'
b00000000000000000000000000000011 (
b010 +
1>
#200000
0>
#205000
1&
b00011 5
b0011 ;
b011111111111111011111111111111111 <
1>
#210000
0>
#215000
0%
0&
0'
1>
#220000
0>
#225000
1%
1>
b00000000000000000000000000000011 ?
#230000
0>
#235000
1&
1>
#240000
0>
#245000
0%
0&
b00000000000000000000000000000011 )
b00000000000000000000000000000011 .
1>
b00000000000000000000000000000000 ?
#250000
0>
#255000
b00000000000000000000000000000000 $
1%
1'
b00000000000000000000000001100100 (
b000 +
1>
#260000
0>
#265000
1&
b00000000000000000000000001100100 3
b001010110011110001110111111111111 <
1>
#270000
0>
#275000
0%
0&
0'
1>
#280000
0>
#285000
b00000000000000000000000000000100 $
1%
1'
b00000000000000000000000011001000 (
b001 +
1>
#290000
0>
#295000
1&
b00000000000000000000000011001000 4
b000000000000000000000000011101100 <
1>
#300000
0>
#305000
0%
0&
0'
1>
#310000
0>
#315000
b00000000000000000000000000001000 $
1%
1'
b00000000000000000000000000010000 (
b010 +
1>
#320000
0>
#325000
1&
b10000 5
1:
b0000 ;
b000000000000000000000000100101100 <
1>
#330000
0>
#335000
0%
0&
0'
b00000000000000000000000100101100 6
19
0:
1>
#340000
0>
#345000
09
1>
#350000
0>
#355000
1>
#360000
0>
#365000
1>
#370000
0>
#375000
1>
#380000
0>
#385000
1>
#390000
0>
#395000
b00000000000000000000000000001100 $
1%
b011 +
1>
b00000000000000000000000100101100 ?
#400000
0>
#405000
1&
1>
#410000
0>
#415000
0%
0&
1>
b00000000000000000000000000000000 ?
#420000
0>
#425000
b00000000000000000000000000010000 $
1%
b100 +
1>
#430000
0>
#435000
1&
1>
#440000
0>
#445000
0%
0&
b00000000000000000000000000000100 )
b00000000000000000000000100101100 /
1>
#450000
0>
#455000
b00000000000000000000000000000000 $
1%
1'
b11111111111111111111111111111111 (
b000 +
1>
#460000
0>
#465000
1&
b11111111111111111111111111111111 3
b100000000000000000000000011000111 <
1>
#470000
0>
#475000
0%
0&
0'
1>
#480000
0>
#485000
b00000000000000000000000000000100 $
1%
1'
b00000000000000000000000000000001 (
b001 +
1>
#490000
0>
#495000
1&
b00000000000000000000000000000001 4
b100000000000000000000000000000000 <
1>
#500000
0>
#505000
0%
0&
0'
1>
#510000
0>
#515000
b00000000000000000000000000001000 $
1%
1'
b00000000000000000000000000010000 (
b010 +
1>
#520000
0>
#525000
1&
1:
1>
#530000
0>
#535000
0%
0&
0'
b00000000000000000000000000000000 6
17
18
19
0:
1>
#540000
0>
#545000
09
1>
#550000
0>
#555000
1>
#560000
0>
#565000
1>
#570000
0>
#575000
1>
#580000
0>
#585000
1>
#590000
0>
#595000
b00000000000000000000000000001100 $
1%
b011 +
1>
#600000
0>
#605000
1&
1>
#610000
0>
#615000
0%
0&
1>
#620000
0>
#625000
b00000000000000000000000000010000 $
1%
b100 +
1>
b00000000000000000000000000000110 ?
#630000
0>
#635000
1&
1>
#640000
0>
#645000
0%
0&
b00000000000000000000000000000111 )
b00000000000000000000000000000000 /
b00000000000000000000000000000110 0
1>
b00000000000000000000000000000000 ?
#650000
0>
#655000
b00000000000000000000000000000000 $
1%
1'
b00000000000000000000000111110100 (
b000 +
1>
#660000
0>
#665000
1&
b00000000000000000000000111110100 3
b000000000000000000000000111110101 <
1>
#670000
0>
#675000
0%
0&
0'
1>
#680000
0>
#685000
b00000000000000000000000000000100 $
1%
1'
b00000000000000000000000011001000 (
b001 +
1>
#690000
0>
#695000
1&
b00000000000000000000000011001000 4
b000000000000000000000001010111100 <
1>
#700000
0>
#705000
0%
0&
0'
1>
#710000
0>
#715000
b00000000000000000000000000001000 $
1%
1'
b00000000000000000000000000010001 (
b010 +
1>
#720000
0>
#725000
1&
b10001 5
1:
b0001 ;
b000000000000000000000000100101100 <
1>
#730000
0>
#735000
0%
0&
0'
b00000000000000000000000100101100 6
07
08
19
0:
1>
#740000
0>
#745000
09
1>
#750000
0>
#755000
1>
#760000
0>
#765000
1>
#770000
0>
#775000
1>
#780000
0>
#785000
1>
#790000
0>
#795000
b00000000000000000000000000001100 $
1%
b011 +
1>
b00000000000000000000000100101100 ?
#800000
0>
#805000
1&
1>
#810000
0>
#815000
0%
0&
1>
b00000000000000000000000000000000 ?
#820000
0>
#825000
b00000000000000000000000000010000 $
1%
b100 +
1>
#830000
0>
#835000
1&
1>
#840000
0>
#845000
0%
0&
b00000000000000000000000000001000 )
b00000000000000000000000100101100 /
b00000000000000000000000000000000 0
1>
#850000
0>
#855000
b00000000000000000000000000000000 $
1%
1'
b11011110101011011011111011101111 (
b000 +
1>
#860000
0>
#865000
1&
b11011110101011011011111011101111 3
b011011110101011011011111000100111 <
1>
#870000
0>
#875000
0%
0&
0'
1>
#880000
0>
#885000
b00000000000000000000000000000100 $
1%
1'
b001 +
1>
#890000
0>
#895000
1&
b11011110101011011011111011101111 4
b000000000000000000000000000000000 <
1>
#900000
0>
#905000
0%
0&
0'
1>
#910000
0>
#915000
b00000000000000000000000000001000 $
1%
1'
b00000000000000000000000000010001 (
b010 +
1>
#920000
0>
#925000
1&
1:
1>
#930000
0>
#935000
0%
0&
0'
b00000000000000000000000000000000 6
17
19
0:
1>
#940000
0>
#945000
09
1>
#950000
0>
#955000
1>
#960000
0>
#965000
1>
#970000
0>
#975000
1>
#980000
0>
#985000
1>
#990000
0>
#995000
b00000000000000000000000000001100 $
1%
b011 +
1>
#1000000
0>
#1005000
1&
1>
#1010000
0>
#1015000
0%
0&
1>
#1020000
0>
#1025000
b00000000000000000000000000010000 $
1%
b100 +
1>
b00000000000000000000000000000010 ?
#1030000
0>
#1035000
1&
1>
#1040000
0>
#1045000
0%
0&
b00000000000000000000000000001010 )
b00000000000000000000000000000000 /
b00000000000000000000000000000010 0
1>
b00000000000000000000000000000000 ?
#1050000
0>
#1055000
b00000000000000000000000000000000 $
1%
1'
b11111111000000001111111100000000 (
b000 +
1>
#1060000
0>
#1065000
1&
b11111111000000001111111100000000 3
b000100000010100110100000000010001 <
1>
#1070000
0>
#1075000
0%
0&
0'
1>
#1080000
0>
#1085000
b00000000000000000000000000000100 $
1%
1'
b00001111111100000000111111110000 (
b001 +
1>
#1090000
0>
#1095000
1&
b00001111111100000000111111110000 4
b011101111000100001110111100010000 <
1>
#1100000
0>
#1105000
0%
0&
0'
1>
#1110000
0>
#1115000
b00000000000000000000000000001000 $
1%
1'
b00000000000000000000000000010010 (
b010 +
1>
#1120000
0>
#1125000
1&
b10010 5
1:
b0010 ;
b000001111000000000000111100000000 <
1>
#1130000
0>
#1135000
0%
0&
0'
b00001111000000000000111100000000 6
07
19
0:
1>
#1140000
0>
#1145000
09
1>
#1150000
0>
#1155000
1>
#1160000
0>
#1165000
1>
#1170000
0>
#1175000
1>
#1180000
0>
#1185000
1>
#1190000
0>
#1195000
b00000000000000000000000000001100 $
1%
b011 +
1>
b00001111000000000000111100000000 ?
#1200000
0>
#1205000
1&
1>
#1210000
0>
#1215000
0%
0&
1>
b00000000000000000000000000000000 ?
#1220000
0>
#1225000
b00000000000000000000000000010000 $
1%
b100 +
1>
#1230000
0>
#1235000
1&
1>
#1240000
0>
#1245000
0%
0&
b00000000000000000000000000001011 )
b00001111000000000000111100000000 /
b00000000000000000000000000000000 0
1>
#1250000
0>
#1255000
b00000000000000000000000000000000 $
1%
1'
b10100000101000001010000010100000 (
b000 +
1>
#1260000
0>
#1265000
1&
b10100000101000001010000010100000 3
b000000000101000000000000010100000 <
1>
#1270000
0>
#1275000
0%
0&
0'
1>
#1280000
0>
#1285000
b00000000000000000000000000000100 $
1%
1'
b00001011000010110000101100001011 (
b001 +
1>
#1290000
0>
#1295000
1&
b00001011000010110000101100001011 4
b000000000000000000000000000000000 <
1>
#1300000
0>
#1305000
0%
0&
0'
1>
#1310000
0>
#1315000
b00000000000000000000000000001000 $
1%
1'
b00000000000000000000000000010011 (
b010 +
1>
#1320000
0>
#1325000
1&
b10011 5
1:
b0011 ;
b010101011101010111010101110101011 <
1>
#1330000
0>
#1335000
0%
0&
0'
b10101011101010111010101110101011 6
19
0:
1>
#1340000
0>
#1345000
09
1>
#1350000
0>
#1355000
1>
#1360000
0>
#1365000
1>
#1370000
0>
#1375000
1>
#1380000
0>
#1385000
1>
#1390000
0>
#1395000
b00000000000000000000000000001100 $
1%
b011 +
1>
b10101011101010111010101110101011 ?
#1400000
0>
#1405000
1&
1>
#1410000
0>
#1415000
0%
0&
1>
b00000000000000000000000000000000 ?
#1420000
0>
#1425000
b00000000000000000000000000010000 $
1%
b100 +
1>
#1430000
0>
#1435000
1&
1>
#1440000
0>
#1445000
0%
0&
b00000000000000000000000000001100 )
b10101011101010111010101110101011 /
1>
#1450000
0>
#1455000
b00000000000000000000000000000000 $
1%
1'
b00010010001101000101011001111000 (
b000 +
1>
#1460000
0>
#1465000
1&
b00010010001101000101011001111000 3
b000011011001111110101111101111011 <
1>
#1470000
0>
#1475000
0%
0&
0'
1>
#1480000
0>
#1485000
b00000000000000000000000000000100 $
1%
1'
b001 +
1>
#1490000
0>
#1495000
1&
b00010010001101000101011001111000 4
b000010010001101000101011001111000 <
1>
#1500000
0>
#1505000
0%
0&
0'
1>
#1510000
0>
#1515000
b00000000000000000000000000001000 $
1%
1'
b00000000000000000000000000010100 (
b010 +
1>
#1520000
0>
#1525000
1&
b10100 5
1:
b0100 ;
b000000000000000000000000000000000 <
1>
#1530000
0>
#1535000
0%
0&
0'
b00000000000000000000000000000000 6
17
19
0:
1>
#1540000
0>
#1545000
09
1>
#1550000
0>
#1555000
1>
#1560000
0>
#1565000
1>
#1570000
0>
#1575000
1>
#1580000
0>
#1585000
1>
#1590000
0>
#1595000
b00000000000000000000000000001100 $
1%
b011 +
1>
#1600000
0>
#1605000
1&
1>
#1610000
0>
#1615000
0%
0&
1>
#1620000
0>
#1625000
b00000000000000000000000000010000 $
1%
b100 +
1>
b00000000000000000000000000000010 ?
#1630000
0>
#1635000
1&
1>
#1640000
0>
#1645000
0%
0&
b00000000000000000000000000001110 )
b00000000000000000000000000000000 /
b00000000000000000000000000000010 0
1>
b00000000000000000000000000000000 ?
#1650000
0>
#1655000
b00000000000000000000000000000000 $
1%
1'
b00000000000000000000000000000001 (
b000 +
1>
#1660000
0>
#1665000
1&
b00000000000000000000000000000001 3
b000010010001101000101011001111001 <
1>
#1670000
0>
#1675000
0%
0&
0'
1>
#1680000
0>
#1685000
b00000000000000000000000000000100 $
1%
1'
b00000000000000000000000000001000 (
b001 +
1>
#1690000
0>
#1695000
1&
b00000000000000000000000000001000 4
b000000000000000000000000000001001 <
1>
#1700000
0>
